{
  "type": "minecraft:block",
  "pools": [
    {
      "rolls": 1.0,
      "entries": [
        {
          "type": "minecraft:item",
          "name": "aoemod:warped_carrots"
        }
      ]
    },
    {
      "rolls": 1.0,
      "entries": [
        {
          "type": "minecraft:item",
          "name": "aoemod:warped_carrots"
        }
      ],
      "conditions": [
        {
          "condition": "minecraft:block_state_property",
          "block": "aoemod:warped_carrots",
          "properties": {
            "age": "7"
          }
        },
        {
          "condition": "minecraft:location_check",
          "predicate": {
            "biome": "#aoemod:tropical_biomes"
          }
        }
      ]
    },
    {
      "rolls": 1.0,
      "entries": [
        {
          "type": "minecraft:item",
          "name": "aoemod:warped_carrots"
        }
      ],
      "conditions": [
        {
          "condition": "minecraft:block_state_property",
          "block": "aoemod:warped_carrots",
          "properties": {
            "age": "7"
          }
        },
        {
          "condition": "minecraft:any_of",
          "terms": [
            {
              "condition": "minecraft:location_check",
              "predicate": {
                "biome": "#aoemod:crimson_biomes"
              }
            },
            {
              "condition": "minecraft:location_check",
              "predicate": {
                "biome": "#aoemod:warped_biomes"
              }
            }
          ]
        },
        {
          "condition": "minecraft:random_chance",
          "chance": 0.5
        }
      ]
    },
    {
      "rolls": 1.0,
      "entries": [
        {
          "type": "minecraft:item",
          "name": "aoemod:warped_carrots"
        }
      ],
      "conditions": [
        {
          "condition": "minecraft:block_state_property",
          "block": "aoemod:warped_carrots",
          "properties": {
            "age": "7"
          }
        },
        {
          "condition": "minecraft:location_check",
          "predicate": {
            "biome": "#aoemod:soul_sand_valley_biomes"
          }
        },
        {
          "condition": "minecraft:random_chance",
          "chance": 0.35
        }
      ]
    },
    {
      "rolls": 1.0,
      "entries": [
        {
          "type": "minecraft:item",
          "name": "aoemod:warped_carrots"
        }
      ],
      "conditions": [
        {
          "condition": "minecraft:block_state_property",
          "block": "aoemod:warped_carrots",
          "properties": {
            "age": "7"
          }
        },
        {
          "condition": "minecraft:location_check",
          "predicate": {
            "biome": "#aoemod:basalt_deltas_biomes"
          }
        },
        {
          "condition": "minecraft:random_chance",
          "chance": 0.2
        }
      ]
    }
  ],
  "functions": [
    {
      "function": "minecraft:explosion_decay"
    }
  ]
}
