{
  "type": "aoemod:random_selector",
  "config": {
    "features": [
      {
        "chance": 0.5,
        "feature": {
          "feature": "aoemod:plains/blobs/andesite",
          "placement": []
        }
      },
      {
        "chance": 0.5,
        "feature": {
          "feature": "aoemod:plains/blobs/calcite",
          "placement": []
        }
      },
      {
        "chance": 0.5,
        "feature": {
          "feature": "aoemod:plains/blobs/clay",
          "placement": []
        }
      },
      {
        "chance": 0.5,
        "feature": {
          "feature": "aoemod:plains/blobs/diorite",
          "placement": []
        }
      },
      {
        "chance": 0.5,
        "feature": {
          "feature": "aoemod:plains/blobs/dirt",
          "placement": []
        }
      },
      {
        "chance": 0.5,
        "feature": {
          "feature": "aoemod:plains/blobs/granite",
          "placement": []
        }
      },
      {
        "chance": 0.5,
        "feature": {
          "feature": "aoemod:plains/blobs/gravel",
          "placement": []
        }
      },
      {
        "chance": 0.5,
        "feature": {
          "feature": "aoemod:plains/blobs/sand",
          "placement": []
        }
      },
      {
        "chance": 0.5,
        "feature": {
          "feature": "aoemod:plains/blobs/sandstone",
          "placement": []
        }
      }
    ]
  }
}